deploy_tools/__init__.py
deploy_tools/__main__.py
deploy_tools/_version.py
deploy_tools/app_builder.py
deploy_tools/build.py
deploy_tools/check_deploy.py
deploy_tools/compare.py
deploy_tools/deploy.py
deploy_tools/layout.py
deploy_tools/module_builder.py
deploy_tools/modulefile.py
deploy_tools/print_updates.py
deploy_tools/snapshot.py
deploy_tools/sync.py
deploy_tools/templater.py
deploy_tools/validate.py
deploy_tools/demo_configuration/settings.yaml
deploy_tools/demo_configuration/dls-pmac-control/0.1.yaml
deploy_tools/demo_configuration/dls-pmac-control/0.2.yaml
deploy_tools/demo_configuration/example-module-apps/0.1.yaml
deploy_tools/demo_configuration/example-module-deps/0.2.yaml
deploy_tools/demo_configuration/phoebus/0.1.yaml
deploy_tools/models/__init__.py
deploy_tools/models/apptainer.py
deploy_tools/models/changes.py
deploy_tools/models/deployment.py
deploy_tools/models/load.py
deploy_tools/models/module.py
deploy_tools/models/parent.py
deploy_tools/models/schema.py
deploy_tools/models/shell.py
deploy_tools/models/schemas/deployment-settings.json
deploy_tools/models/schemas/deployment.json
deploy_tools/models/schemas/module.json
deploy_tools/models/schemas/release.json
deploy_tools/templates/apptainer_entrypoint
deploy_tools/templates/modulefile
deploy_tools/templates/modulefile_version
deploy_tools/templates/shell_entrypoint
dls_deploy_tools-0.4.dist-info/LICENSE
dls_deploy_tools-0.4.dist-info/METADATA
dls_deploy_tools-0.4.dist-info/WHEEL
dls_deploy_tools-0.4.dist-info/entry_points.txt
dls_deploy_tools-0.4.dist-info/top_level.txt
dls_deploy_tools-0.4.dist-info/RECORD
